cvss_rescore/__init__.py
cvss_rescore/cvsslib.py
cvss_rescore/manualVettingException.py
cvss_rescore-0.0.5.dist-info/LICENSE.txt
cvss_rescore-0.0.5.dist-info/METADATA
cvss_rescore-0.0.5.dist-info/WHEEL
cvss_rescore-0.0.5.dist-info/top_level.txt
cvss_rescore-0.0.5.dist-info/RECORD
