Metadata-Version: 2.1
Name: cvss-rescore
Version: 0.0.5
Summary: Rescore cvss3 and 3.1 results from any json file based on custom rules that you create.
Home-page: https://github.com/bp4151/cvss-rescore/
Author: Bruce Parr
Author-email: bp4151@gmail.com
License: MIT
Project-URL: Documentation, https://cvss-rescore.readthedocs.io/en/latest/
Project-URL: Source, https://github.com/bp4151/cvss-rescore/
Project-URL: Download, https://pypi.org/project/cvss-rescore/#files
Platform: any
Classifier: Development Status :: 4 - Beta
Classifier: Programming Language :: Python
License-File: LICENSE.txt
Requires-Dist: importlib-metadata ; python_version < "3.8"
Requires-Dist: cvss ; python_version >= "3.6"
Requires-Dist: rule-engine ; python_version >= "3.6"
Provides-Extra: testing
Requires-Dist: setuptools ; extra == 'testing'
Requires-Dist: pytest ; extra == 'testing'
Requires-Dist: pytest-cov ; extra == 'testing'
